sphinx_resolve_py_references/__init__.py
sphinx_resolve_py_references/extension.py
sphinx_resolve_py_references/resolver.py
sphinx_resolve_py_references/utils.py
sphinx_resolve_py_references-0.1.0.dist-info/LICENSE
sphinx_resolve_py_references-0.1.0.dist-info/METADATA
sphinx_resolve_py_references-0.1.0.dist-info/WHEEL
sphinx_resolve_py_references-0.1.0.dist-info/top_level.txt
sphinx_resolve_py_references-0.1.0.dist-info/RECORD
