Metadata-Version: 2.1
Name: sphinx-resolve-py-references
Version: 0.1.0
Summary: Better python object resolution in Sphinx
Home-page: https://github.com/23andMe/sphinx-resolve-py-references
Author: Ryan Morshead
Author-email: ryan.morshead@gmail.com
License: BSD
Keywords: Sphinx
Platform: Linux
Platform: Mac OS X
Platform: Windows
Classifier: Framework :: Sphinx :: Extension
Classifier: Operating System :: OS Independent
Classifier: Intended Audience :: Developers
Classifier: Programming Language :: Python :: 3.7
Classifier: Programming Language :: Python :: 3.8
Classifier: Programming Language :: Python :: 3.9
Requires-Python: >=3.7
Requires-Dist: sphinx
